hpfracc/__init__.py
hpfracc/algorithms/__init__.py
hpfracc/algorithms/advanced_methods.py
hpfracc/algorithms/advanced_optimized_methods.py
hpfracc/algorithms/gpu_optimized_methods.py
hpfracc/algorithms/integral_methods.py
hpfracc/algorithms/novel_derivatives.py
hpfracc/algorithms/optimized_methods.py
hpfracc/algorithms/parallel_optimized_methods.py
hpfracc/algorithms/special_methods.py
hpfracc/algorithms/special_optimized_methods.py
hpfracc/analytics/__init__.py
hpfracc/analytics/analytics_manager.py
hpfracc/analytics/error_analyzer.py
hpfracc/analytics/performance_monitor.py
hpfracc/analytics/usage_tracker.py
hpfracc/analytics/workflow_insights.py
hpfracc/benchmarks/benchmark_runner.py
hpfracc/benchmarks/ml_performance_benchmark.py
hpfracc/core/__init__.py
hpfracc/core/definitions.py
hpfracc/core/derivatives.py
hpfracc/core/fractional_implementations.py
hpfracc/core/fractional_implementations_backup.py
hpfracc/core/integrals.py
hpfracc/core/utilities.py
hpfracc/ml/__init__.py
hpfracc/ml/adjoint_optimization.py
hpfracc/ml/backends.py
hpfracc/ml/core.py
hpfracc/ml/data.py
hpfracc/ml/fractional_autograd.py
hpfracc/ml/gnn_layers.py
hpfracc/ml/gnn_models.py
hpfracc/ml/gpu_optimization.py
hpfracc/ml/layers.py
hpfracc/ml/losses.py
hpfracc/ml/neural_ode.py
hpfracc/ml/optimizers.py
hpfracc/ml/probabilistic_fractional_orders.py
hpfracc/ml/registry.py
hpfracc/ml/spectral_autograd.py
hpfracc/ml/spectral_autograd_api.md
hpfracc/ml/stochastic_memory_sampling.py
hpfracc/ml/tensor_ops.py
hpfracc/ml/training.py
hpfracc/ml/variance_aware_training.py
hpfracc/ml/workflow.py
hpfracc/solvers/__init__.py
hpfracc/solvers/advanced_solvers.py
hpfracc/solvers/ode_solvers.py
hpfracc/solvers/pde_solvers.py
hpfracc/solvers/predictor_corrector.py
hpfracc/special/__init__.py
hpfracc/special/binomial_coeffs.py
hpfracc/special/gamma_beta.py
hpfracc/special/mittag_leffler.py
hpfracc/utils/__init__.py
hpfracc/utils/error_analysis.py
hpfracc/utils/memory_management.py
hpfracc/utils/plotting.py
hpfracc-2.0.0.dist-info/licenses/LICENSE
hpfracc-2.0.0.dist-info/METADATA
hpfracc-2.0.0.dist-info/WHEEL
hpfracc-2.0.0.dist-info/top_level.txt
hpfracc-2.0.0.dist-info/RECORD
