Metadata-Version: 2.4
Name: hpfracc
Version: 2.0.0
Summary: High-Performance Fractional Calculus Library with Fractional Autograd Framework, GPU Acceleration, Machine Learning Integration, and Graph Neural Networks
Author-email: "Davian R. Chin" <d.r.chin@pgr.reading.ac.uk>
Maintainer-email: "Davian R. Chin" <d.r.chin@pgr.reading.ac.uk>
License-Expression: MIT
Project-URL: Homepage, https://github.com/dave2k77/fractional_calculus_library
Project-URL: Repository, https://github.com/dave2k77/fractional_calculus_library.git
Project-URL: Documentation, https://fractional-calculus-library.readthedocs.io
Project-URL: Bug Tracker, https://github.com/dave2k77/fractional_calculus_library/issues
Project-URL: Source Code, https://github.com/dave2k77/fractional_calculus_library
Project-URL: Download, https://github.com/dave2k77/fractional_calculus_library/releases
Project-URL: Academic Contact, https://www.reading.ac.uk/people/d.r.chin
Keywords: fractional-calculus,numerical-methods,machine-learning,graph-neural-networks,autograd,spectral-methods,stochastic-optimization,jax,pytorch,numba,scientific-computing,mathematics,deep-learning
Classifier: Development Status :: 5 - Production/Stable
Classifier: Intended Audience :: Science/Research
Classifier: Intended Audience :: Education
Classifier: Intended Audience :: Developers
Classifier: Programming Language :: Python :: 3
Classifier: Programming Language :: Python :: 3.8
Classifier: Programming Language :: Python :: 3.9
Classifier: Programming Language :: Python :: 3.10
Classifier: Programming Language :: Python :: 3.11
Classifier: Topic :: Scientific/Engineering :: Mathematics
Classifier: Topic :: Scientific/Engineering :: Physics
Classifier: Topic :: Scientific/Engineering :: Artificial Intelligence
Classifier: Topic :: Software Development :: Libraries :: Python Modules
Classifier: Operating System :: OS Independent
Requires-Python: >=3.8
License-File: LICENSE
Requires-Dist: numpy>=1.21.0
Requires-Dist: scipy>=1.7.0
Requires-Dist: matplotlib>=3.5.0
Requires-Dist: jax>=0.4.0
Requires-Dist: jaxlib>=0.4.0
Requires-Dist: optax>=0.1.0
Requires-Dist: torch>=1.12.0
Requires-Dist: numba>=0.56.0
Requires-Dist: multiprocessing-logging>=0.3.0
Requires-Dist: joblib>=1.1.0
Requires-Dist: sympy>=1.10.0
Requires-Dist: pandas>=1.3.0
Requires-Dist: seaborn>=0.11.0
Requires-Dist: pytest>=6.0.0
Requires-Dist: pytest-benchmark>=3.4.0
Requires-Dist: pytest-cov>=3.0.0
Requires-Dist: sphinx>=4.0.0
Requires-Dist: sphinx-rtd-theme>=1.0.0
Requires-Dist: black>=22.0.0
Requires-Dist: flake8>=4.0.0
Requires-Dist: mypy>=0.950
Requires-Dist: pre-commit>=2.15.0
Provides-Extra: dev
Requires-Dist: pytest>=6.0.0; extra == "dev"
Requires-Dist: pytest-benchmark>=3.4.0; extra == "dev"
Requires-Dist: pytest-cov>=3.0.0; extra == "dev"
Requires-Dist: black>=22.0.0; extra == "dev"
Requires-Dist: flake8>=4.0.0; extra == "dev"
Requires-Dist: mypy>=0.950; extra == "dev"
Requires-Dist: pre-commit>=2.15.0; extra == "dev"
Requires-Dist: jupyter>=1.0.0; extra == "dev"
Requires-Dist: ipykernel>=6.0.0; extra == "dev"
Provides-Extra: docs
Requires-Dist: sphinx>=4.0.0; extra == "docs"
Requires-Dist: sphinx-rtd-theme>=1.0.0; extra == "docs"
Requires-Dist: myst_parser>=0.18.0; extra == "docs"
Requires-Dist: sphinx-autodoc-typehints>=1.12.0; extra == "docs"
Requires-Dist: pygments>=2.10.0; extra == "docs"
Provides-Extra: gpu
Requires-Dist: cupy>=10.0.0; extra == "gpu"
Requires-Dist: cudf>=21.0.0; extra == "gpu"
Provides-Extra: ml
Requires-Dist: torch>=1.12.0; extra == "ml"
Requires-Dist: jax>=0.4.0; extra == "ml"
Requires-Dist: jaxlib>=0.4.0; extra == "ml"
Requires-Dist: numba>=0.56.0; extra == "ml"
Dynamic: license-file
